sisu_gmail/__init__.py
sisu_gmail/auth.py
sisu_gmail/create.py
sisu_gmail/delete.py
sisu_gmail/label.py
sisu_gmail/read.py
sisu_gmail/search.py
sisu_gmail/send.py
sisu_gmail/user.py
sisu_gmail-0.0.4b0.dist-info/LICENSE
sisu_gmail-0.0.4b0.dist-info/METADATA
sisu_gmail-0.0.4b0.dist-info/WHEEL
sisu_gmail-0.0.4b0.dist-info/top_level.txt
sisu_gmail-0.0.4b0.dist-info/RECORD
